README.md
setup.py
dyst/__init__.py
dyst/dyst
dyst.egg-info/PKG-INFO
dyst.egg-info/SOURCES.txt
dyst.egg-info/dependency_links.txt
dyst.egg-info/top_level.txt