Metadata-Version: 1.1
Name: dyst
Version: 0.0.5
Summary: Dyst Dynamic histograms in the terminal
Home-page: https://github.com/coelias/dyst
Author: Carlos del Ojo Elias
Author-email: deepbit@gmail.com
License: GPLv3
Keywords: plotting interactive terminal histogram chart realtime dynamic
Platform: UNKNOWN
Classifier: Development Status :: 5 - Production/Stable
Classifier: Intended Audience :: Science/Research
Classifier: Topic :: Scientific/Engineering :: Visualization
Classifier: License :: OSI Approved :: GNU General Public License v3 or later (GPLv3+)
Classifier: Programming Language :: Python :: 2
Classifier: Programming Language :: Python :: 3
